<window id="2901">
	<defaultcontrol>4</defaultcontrol>
	<include>dialogeffect</include>
	<animation type="WindowOpen">
		<effect type="slide" start="0,100" end="0" time="400" />
		<effect type="fade" time="200" />
	</animation>
	<animation type="WindowClose">
		<effect type="slide" start="0" end="0,100" time="400" />
		<effect type="fade" time="200" />
	</animation>
	<controls>

<control type="image" id="3">
      <description>Background</description>
      <posx>0</posx>
      <posy>120</posy>
      <width>1280</width>
      <height>600</height>
      <texture>PlayBg.png</texture>
</control>


<control type="button" id="4">
      <description>My first button control</description>
      <posx>300</posx>
      <posy>650</posy>
      <height>60</height>
      <width>200</width>
		<visible>Player.Paused</visible>
      <colordiffuse>FFFFFFFF</colordiffuse>
      <texturefocus>PPlayOn.png</texturefocus>
      <texturenofocus>PPlayOff.png</texturenofocus>
      <label>-</label>
      <font>font5</font>
      <textcolor>FFFFFFFF</textcolor>
      <disabledcolor>80FFFFFF</disabledcolor>
      <align></align>
      <aligny></aligny>
      <textoffsetx></textoffsetx>
      <textoffsety></textoffsety>
      <pulseonselect></pulseonselect>
      <onclick>XBMC.PlayerControl(Play)</onclick>
      <onright>5</onright>
</control>

<control type="button" id="4">
      <description>My first button control</description>
      <posx>300</posx>
      <posy>650</posy>
      <height>60</height>
      <width>200</width>
		<visible>!Player.Paused</visible>
      <colordiffuse>FFFFFFFF</colordiffuse>
      <texturefocus>PPauseOn.png</texturefocus>
      <texturenofocus>PPauseOff.png</texturenofocus>
      <label>-</label>
      <font>font5</font>
      <textcolor>FFFFFFFF</textcolor>
      <disabledcolor>80FFFFFF</disabledcolor>
      <align></align>
      <aligny></aligny>
      <textoffsetx></textoffsetx>
      <textoffsety></textoffsety>
      <pulseonselect></pulseonselect>
      <onclick>XBMC.PlayerControl(Play)</onclick>
      <onfocus>-</onfocus>
      <onright>5</onright>
</control>

<control type="button" id="5">
      <description>My first button control</description>
      <posx>500</posx>
      <posy>650</posy>
      <height>60</height>
      <width>200</width>
      <colordiffuse>FFFFFFFF</colordiffuse>
      <texturefocus>PStopOn.png</texturefocus>
      <texturenofocus>PStopOff.png</texturenofocus>
      <label>-</label>
      <font>font5</font>
      <textcolor>FFFFFFFF</textcolor>
      <disabledcolor>80FFFFFF</disabledcolor>
      <align></align>
      <aligny></aligny>
      <textoffsetx></textoffsetx>
      <textoffsety></textoffsety>
      <pulseonselect></pulseonselect>
      <onclick>XBMC.PlayerControl(Stop)</onclick>
      <onfocus>-</onfocus>
      <onup>2</onup>
      <ondown>3</ondown>
      <onleft>4</onleft>
      <onright>6</onright>
</control>

<control type="button" id="6">
      <description>My first button control</description>
      <posx>700</posx>
      <posy>650</posy>
      <height>60</height>
      <width>200</width>
      <colordiffuse>FFFFFFFF</colordiffuse>
      <texturefocus>PVideoOn.png</texturefocus>
      <texturenofocus>PVideoOff.png</texturenofocus>
      <label>-</label>
      <font>font5</font>
      <align></align>
      <aligny></aligny>
      <textoffsetx></textoffsetx>
      <textoffsety></textoffsety>
      <pulseonselect></pulseonselect>
      <onclick>XBMC.ActivateWindow(123)</onclick>
      <onleft>5</onleft>
      <onright>7</onright>
</control>

<control type="button" id="7">
      <description>My first button control</description>
      <posx>900</posx>
      <posy>650</posy>
      <height>60</height>
      <width>200</width>
      <colordiffuse>FFFFFFFF</colordiffuse>
      <texturefocus>PAudioOn.png</texturefocus>
      <texturenofocus>PAudioOff.png</texturenofocus>
      <label>-</label>
      <font>font5</font>
      <align></align>
      <aligny></aligny>
      <textoffsetx></textoffsetx>
      <textoffsety></textoffsety>
      <pulseonselect></pulseonselect>
      <onclick>XBMC.ActivateWindow(124)</onclick>
      <onleft>6</onleft>

</control>

		<control type="progress" id="23">
			<description>Progressbar</description>
			<posx>140</posx>
			<posy>640</posy>
			<width>1000</width>
			<height>10</height>
			<info>Player.Progress</info>
			<texturebg>PlayBarbg.png</texturebg>
			<lefttexture>play_01.png</lefttexture>
			<midtexture>play_02.png</midtexture>
			<righttexture>play_03.png</righttexture>
			<overlaytexture>-</overlaytexture>
		</control>

			<control type="label" id="1">
				<description>time label</description>
				<posx>122</posx>
				<posy>636</posy>
<textcolor>FFffffff</textcolor>
				<label>$INFO[VideoPlayer.Time]</label>
				<align>right</align>
				<font>font5</font>
			</control>

			<control type="label" id="1">
				<description>time label</description>
				<posx>1160</posx>
				<posy>636</posy>
<textcolor>FFffffff</textcolor>
				<label>$INFO[Player.Duration]</label>
				<align>left</align>
				<font>font5</font>
			</control>

	</controls>
</window>